safetywrap/__init__.py
safetywrap/_impl.py
safetywrap/_interface.py
safetywrap/py.typed
safetywrap-1.5.0.dist-info/LICENSE
safetywrap-1.5.0.dist-info/METADATA
safetywrap-1.5.0.dist-info/WHEEL
safetywrap-1.5.0.dist-info/top_level.txt
safetywrap-1.5.0.dist-info/RECORD
