Metadata-Version: 2.1
Name: safetywrap
Version: 1.5.0
Summary: Rust-inspired typesafe result types
Home-page: https://www.github.com/mplanchard/safetywrap
Author: Matthew Planchard
Author-email: msplanchard@gmail.com
License: UNKNOWN
Keywords: python,rust,result,option,typed,types,typesafe,monad,wrapper,safety
Platform: UNKNOWN
Classifier: Development Status :: 4 - Beta
Classifier: Intended Audience :: Developers
Classifier: License :: OSI Approved :: Apache Software License
Classifier: Natural Language :: English
Classifier: Operating System :: POSIX :: Linux
Classifier: Operating System :: MacOS :: MacOS X
Classifier: Operating System :: Microsoft :: Windows
Classifier: Programming Language :: Python
Classifier: Programming Language :: Python :: 3 :: Only
Classifier: Programming Language :: Python :: 3.6
Classifier: Programming Language :: Python :: 3.7
Classifier: Programming Language :: Python :: 3.8
Requires-Python: >=3.6
Provides-Extra: dev
Requires-Dist: black ; extra == 'dev'
Requires-Dist: coverage ; extra == 'dev'
Requires-Dist: flake8 ; extra == 'dev'
Requires-Dist: ipdb ; extra == 'dev'
Requires-Dist: ipython ; extra == 'dev'
Requires-Dist: mypy ; extra == 'dev'
Requires-Dist: pydocstyle ; extra == 'dev'
Requires-Dist: pylint ; extra == 'dev'
Requires-Dist: pytest ; extra == 'dev'
Requires-Dist: pytest-cov ; extra == 'dev'
Requires-Dist: tox ; extra == 'dev'
Requires-Dist: twine ; extra == 'dev'
Requires-Dist: typeguard ; extra == 'dev'
Requires-Dist: wheel ; extra == 'dev'
